vision_spell/__init__.py
vision_spell/image.py
vision_spell/script.py
vision_spell/types.py
vision_spell/video.py
vision_spell-0.1.2.dist-info/METADATA
vision_spell-0.1.2.dist-info/WHEEL
vision_spell-0.1.2.dist-info/top_level.txt
vision_spell-0.1.2.dist-info/RECORD
