Metadata-Version: 2.4
Name: vision-spell
Version: 0.1.2
Summary: private package
Requires-Python: >=3.12
Requires-Dist: fal-client>=0.7.0
Requires-Dist: python-dotenv>=1.1.1
Requires-Dist: ipykernel<7.0.0,>=6.29.5
Requires-Dist: google-genai>=1.28.0
Requires-Dist: ruamel-yaml>=0.18.14
Requires-Dist: opencv-python>=4.12.0.88
Requires-Dist: moviepy>=2.2.1
